teletiffinfo/__init__.py
teletiffinfo/tiff.py
teletiffinfo/util.py
teletiffinfo-0.0.4.dist-info/LICENSE
teletiffinfo-0.0.4.dist-info/METADATA
teletiffinfo-0.0.4.dist-info/WHEEL
teletiffinfo-0.0.4.dist-info/top_level.txt
teletiffinfo-0.0.4.dist-info/RECORD
