Metadata-Version: 2.1
Name: teletiffinfo
Version: 0.0.4
Summary: Fetch metadata from remote (https) tiff.
Home-page: https://github.com/xgui3783/teletiffinfo
Author: Xiao Gui
Author-email: xgui3783@gmail.com
License: UNKNOWN
Platform: UNKNOWN
License-File: LICENSE
Requires-Dist: requests (>=2.26.0)
Requires-Dist: dataclasses ; python_version < "3.7"
